uart.v
module uart_tx (tx_data_IN, tx_data_OUT, baud_tick, reset);
    input baud_tick;
    input reset;
    input [7:0] tx_data_IN;
    output reg tx_data_OUT;
    
    reg start_bit = 0;
    reg [7:0] tx_data_IN_shift;
    always @(posedge reset) begin
        if(reset) begin
            tx_data_IN_shift <= tx_data_IN;
            $display("%d, %d", tx_data_IN_shift, tx_data_IN);
        end
    end

    reg start = 0;
    always @(posedge baud_tick) begin
        // $display("%d", tx_data_IN_shift);
        if (start == 0) begin
            start <= 1;
            tx_data_OUT <= start_bit;
        end
        else begin
            tx_data_OUT <= tx_data_IN_shift[0];
            tx_data_IN_shift <= tx_data_IN_shift >> 1;
            // $display("%0d, %0d", tx_data_OUT, tx_data_IN_shift);
        end
    end
endmodule


module uart_rx (rx_data_IN, rx_data_OUT, baud_tick);
    input baud_tick;
    input rx_data_IN;
    output reg rx_data_OUT = 1;

    reg start = 0;
    always @(negedge rx_data_IN) begin
        if (start == 0) begin
            start <= 1;
            rx_data_OUT <= 0;
        end
        else begin
            rx_data_OUT <= 1; // output remains high when no data is received
        end
    end

    reg [3:0] ctr = 0;
    always @(posedge baud_tick) begin
        if (start && ctr != 8) begin
            #1; // start sampling for data after 1us after the baud_tick is detected. 
            rx_data_OUT <= rx_data_IN;
            ctr <= ctr + 1;
        end
        if (ctr == 8) begin
            rx_data_OUT <= 1; // output remains high when no data is received
        end
    end  
endmodule

uart_tb.v
`timescale 1us/1us
`include "uart.v"

module uart_tb;
    reg reset = 0;
    initial begin
        $dumpfile("uart.vcd");
        $dumpvars(0, uart_tb);
        #10 reset = 1;
        #10 reset = 0;
        #5000000 $stop;
    end

    reg baud_tick = 0;
    always #52 baud_tick = !baud_tick;

    reg [7:0] tx_data_IN = 8'b10011011; // data to transmit goes here
    wire tx_data_OUT;
    wire rx_data_OUT;
    uart_tx tx (tx_data_IN, tx_data_OUT, baud_tick, reset);
    uart_rx rx (tx_data_OUT, rx_data_OUT, baud_tick);
endmodule

uart/uart.vcd
$date
	Mon Nov 11 02:51:42 2024
$end
$version
	Icarus Verilog
$end
$timescale
	1us
$end
$scope module uart_tb $end
$var wire 1 ! tx_data_OUT $end
$var wire 1 " rx_data_OUT $end
$var reg 1 # baud_tick $end
$var reg 1 $ reset $end
$var reg 8 % tx_data_IN [7:0] $end
$scope module rx $end
$var wire 1 # baud_tick $end
$var wire 1 ! rx_data_IN $end
$var reg 4 & ctr [3:0] $end
$var reg 1 " rx_data_OUT $end
$var reg 1 ' start $end
$upscope $end
$scope module tx $end
$var wire 1 # baud_tick $end
$var wire 1 $ reset $end
$var wire 8 ( tx_data_IN [7:0] $end
$var reg 1 ) start $end
$var reg 1 * start_bit $end
$var reg 8 + tx_data_IN_shift [7:0] $end
$var reg 1 ! tx_data_OUT $end
$upscope $end
$upscope $end
$enddefinitions $end
$comment Show the parameter values. $end
$dumpall
$end
#0
$dumpvars
bx +
0*
0)
b10011011 (
0'
b0 &
b10011011 %
0$
0#
1"
x!
$end
#10
b10011011 +
1$
#20
0$
#52
0"
1'
0!
1)
1#
#104
0#
#156
b1001101 +
1!
1#
#157
b1 &
1"
#208
0#
#260
b100110 +
1#
#261
b10 &
#312
0#
#364
b10011 +
0!
1#
#365
b11 &
0"
#416
0#
#468
b1001 +
1!
1#
#469
b100 &
1"
#520
0#
#572
b100 +
1#
#573
b101 &
#624
0#
#676
b10 +
0!
1#
#677
b110 &
0"
#728
0#
#780
b1 +
1#
#781
b111 &
#832
0#
#884
b0 +
1!
1#
#885
b1000 &
1"
#936
0#
#988
0!
1#
#1040
0#
#1092
1#
#1144
0#
#1196
1#
#1248
0#
#1300
1#
#1352
0#
#1404
1#
#1456
0#
#1508
1#
#1560
0#
#1612
1#
#1664
0#
#1716
1#
#1768
0#
#1820
1#
#1872
0#
#1924
1#
#1976
0#
#2028
1#
#2080
0#
#2132
1#
#2184
0#
#2236
1#
#2288
0#
#2340
1#
#2392
0#
#2444
1#
#2496
0#
#2548
1#
#2600
0#
#2652
1#
#2704
0#
#2756
1#
#2808
0#
#2860
1#
#2912
0#
#2964
1#
#3016
0#
#3068
1#
#3120
0#
#3172
1#
#3224
0#
#3276
1#
#3328
0#
#3380
1#
#3432
0#
#3484
1#
#3536
0#
#3588
1#
#3640
0#
#3692
1#
#3744
0#
#3796
1#
#3848
0#
#3900
1#
#3952
0#
#4004
1#
#4056
0#
#4108
1#
#4160
0#
#4212
1#
#4264
0#
#4316
1#
#4368
0#
#4420
1#
#4472
0#
#4524
1#
#4576
0#
#4628
1#
#4680
0#
#4732
1#
#4784
0#
#4836
1#
#4888
0#
#4940
1#
#4992
0#
#5044
1#
#5096
0#
#5148
1#
#5200
0#
#5252
1#
#5304
0#
#5356
1#
#5408
0#
#5460
1#
#5512
0#
#5564
1#
#5616
0#
#5668
1#
#5720
0#
#5772
1#
#5824
0#
#5876
1#
#5928
0#
#5980
1#
#6032
0#
#6084
1#
#6136
0#
#6188
1#
#6240
0#
#6292
1#
#6344
0#
#6396
1#
#6448
0#
#6500
1#
#6552
0#
#6604
1#
#6656
0#
#6708
1#
#6760
0#
#6812
1#
#6864
0#
#6916
1#
#6968
0#
#7020
1#
#7072
0#
#7124
1#
#7176
0#
#7228
1#
#7280
0#
#7332
1#
#7384
0#
#7436
1#
#7488
0#
#7540
1#
#7592
0#
#7644
1#
#7696
0#
#7748
1#
#7800
0#
#7852
1#
#7904
0#
#7956
1#
#8008
0#
#8060
1#
#8112
0#
#8164
1#
#8216
0#
#8268
1#
#8320
0#
#8372
1#
#8424
0#
#8476
1#
#8528
0#
#8580
1#
#8632
0#
#8684
1#
#8736
0#
#8788
1#
#8840
0#
#8892
1#
#8944
0#
#8996
1#
#9048
0#
#9100
1#
#9152
0#
#9204
1#
#9256
0#
#9308
1#
#9360
0#
#9412
1#
#9464
0#
#9516
1#
#9568
0#
#9620
1#
#9672
0#
#9724
1#
#9776
0#
#9828
1#
#9880
0#
#9932
1#
#9984
0#
#10036
1#
#10088
0#
#10140
1#
#10192
0#
#10244
1#
#10296
0#
#10348
1#
#10400
0#
#10452
1#
#10504
0#
#10556
1#
#10608
0#
#10660
1#
#10712
0#
#10764
1#
#10816
0#
#10868
1#
#10920
0#
#10972
1#
#11024
0#
#11076
1#
#11128
0#
#11180
1#
#11232
0#
#11284
1#
#11336
0#
#11388
1#
#11440
0#
#11492
1#
#11544
0#
#11596
1#
#11648
0#
#11700
1#
#11752
0#
#11804
1#
#11856
0#
#11908
1#
#11960
0#
#12012
1#
#12064
0#
#12116
1#
#12168
0#
#12220
1#
#12272
0#
#12324
1#
#12376
0#
#12428
1#
#12480
0#
#12532
1#
#12584
0#
#12636
1#
#12688
0#
#12740
1#
#12792
0#
#12844
1#
#12896
0#
#12948
1#
#13000
0#
#13052
1#
#13104
0#
#13156
1#
#13208
0#
#13260
1#
#13312
0#
#13364
1#
#13416
0#
#13468
1#
#13520
0#
#13572
1#
#13624
0#
#13676
1#
#13728
0#
#13780
1#
#13832
0#
#13884
1#
#13936
0#
#13988
1#
#14040
0#
#14092
1#
#14144
0#
#14196
1#
#14248
0#
#14300
1#
#14352
0#
#14404
1#
#14456
0#
#14508
1#
#14560
0#
#14612
1#
#14664
0#
#14716
1#
#14768
0#
#14820
1#
#14872
0#
#14924
1#
#14976
0#
#15028
1#
#15080
0#
#15132
1#
#15184
0#
#15236
1#
#15288
0#
#15340
1#
#15392
0#
#15444
1#
#15496
0#
#15548
1#
#15600
0#
#15652
1#
#15704
0#
#15756
1#
#15808
0#
#15860
1#
#15912
0#
#15964
1#
#16016
0#
#16068
1#
#16120
0#
#16172
1#
#16224
0#
#16276
1#
#16328
0#
#16380
1#
#16432
0#
#16484
1#
#16536
0#
#16588
1#
#16640
0#
#16692
1#
#16744
0#
#16796
1#
#16848
0#
#16900
1#
#16952
0#
#17004
1#
#17056
0#
#17108
1#
#17160
0#
#17212
1#
#17264
0#
#17316
1#
#17368
0#
#17420
1#
#17472
0#
#17524
1#
#17576
0#
#17628
1#
#17680
0#
#17732
1#
#17784
0#
#17836
1#
#17888
0#
#17940
1#
#17992
0#
#18044
1#
#18096
0#
#18148
1#
#18200
0#
#18252
1#
#18304
0#
#18356
1#
#18408
0#
#18460
1#
#18512
0#
#18564
1#
#18616
0#
#18668
1#
#18720
0#
#18772
1#
#18824
0#
#18876
1#
#18928
0#
#18980
1#
#19032
0#
#19084
1#
#19136
0#
#19188
1#
#19240
0#
#19292
1#
#19344
0#
#19396
1#
#19448
0#
#19500
1#
#19552
0#
#19604
1#
#19656
0#
#19708
1#
#19760
0#
#19812
1#
#19864
0#
#19916
1#
#19968
0#
#20020
1#
#20072
0#
#20124
1#
#20176
0#
#20228
1#
#20280
0#
#20332
1#
#20384
0#
#20436
1#
#20488
0#
#20540
1#
#20592
0#
#20644
1#
#20696
0#
#20748
1#
#20800
0#
#20852
1#
#20904
0#
#20956
1#
#21008
0#
#21060
1#
#21112
0#
#21164
1#
#21216
0#
#21268
1#
#21320
0#
#21372
1#
#21424
0#
#21476
1#
#21528
0#
#21580
1#
#21632
0#
#21684
1#
#21736
0#
#21788
1#
#21840
0#
#21892
1#
#21944
0#
#21996
1#
#22048
0#
#22100
1#
#22152
0#
#22204
1#
#22256
0#
#22308
1#
#22360
0#
#22412
1#
#22464
0#
#22516
1#
#22568
0#
#22620
1#
#22672
0#
#22724
1#
#22776
0#
#22828
1#
#22880
0#
#22932
1#
#22984
0#
#23036
1#
#23088
0#
#23140
1#
#23192
0#
#23244
1#
#23296
0#
#23348
1#
#23400
0#
#23452
1#
#23504
0#
#23556
1#
#23608
0#
#23660
1#
#23712
0#
#23764
1#
#23816
0#
#23868
1#
#23920
0#
#23972
1#
#24024
0#
#24076
1#
#24128
0#
#24180
1#
#24232
0#
#24284
1#
#24336
0#
#24388
1#
#24440
0#
#24492
1#
#24544
0#
#24596
1#
#24648
0#
#24700
1#
#24752
0#
#24804
1#
#24856
0#
#24908
1#
#24960
0#
#25012
1#
#25064
0#
#25116
1#
#25168
0#
#25220
1#
#25272
0#
#25324
1#
#25376
0#
#25428
1#
#25480
0#
#25532
1#
#25584
0#
#25636
1#
#25688
0#
#25740
1#
#25792
0#
#25844
1#
#25896
0#
#25948
1#
#26000
0#
#26052
1#
#26104
0#
#26156
1#
#26208
0#
#26260
1#
#26312
0#
#26364
1#
#26416
0#
#26468
1#
#26520
0#
#26572
1#
#26624
0#
#26676
1#
#26728
0#
#26780
1#
#26832
0#
#26884
1#
#26936
0#
#26988
1#
#27040
0#
#27092
1#
#27144
0#
#27196
1#
#27248
0#
#27300
1#
#27352
0#
#27404
1#
#27456
0#
#27508
1#
#27560
0#
#27612
1#
#27664
0#
#27716
1#
#27768
0#
#27820
1#
#27872
0#
#27924
1#
#27976
0#
#28028
1#
#28080
0#
#28132
1#
#28184
0#
#28236
1#
#28288
0#
#28340
1#
#28392
0#
#28444
1#
#28496
0#
#28548
1#
#28600
0#
#28652
1#
#28704
0#
#28756
1#
#28808
0#
#28860
1#
#28912
0#
#28964
1#
#29016
0#
#29068
1#
#29120
0#
#29172
1#
#29224
0#
#29276
1#
#29328
0#
#29380
1#
#29432
0#
#29484
1#
#29536
0#
#29588
1#
#29640
0#
#29692
1#
#29744
0#
#29796
1#
#29848
0#
#29900
1#
#29952
0#
#30004
1#
#30056
0#
#30108
1#
#30160
0#
#30212
1#
#30264
0#
#30316
1#
#30368
0#
#30420
1#
#30472
0#
#30524
1#
#30576
0#
#30628
1#
#30680
0#
#30732
1#
#30784
0#
#30836
1#
#30888
0#
#30940
1#
#30992
0#
#31044
1#
#31096
0#
#31148
1#
#31200
0#
#31252
1#
#31304
0#
#31356
1#
#31408
0#
#31460
1#
#31512
0#
#31564
1#
#31616
0#
#31668
1#
#31720
0#
#31772
1#
#31824
0#
#31876
1#
#31928
0#
#31980
1#
#32032
0#
#32084
1#
#32136
0#
#32188
1#
#32240
0#
#32292
1#
#32344
0#
#32396
1#
#32448
0#
#32500
1#
#32552
0#
#32604
1#
#32656
0#
#32708
1#
#32760
0#
#32812
1#
#32864
0#
#32916
1#
#32968
0#
#33020
1#
#33072
0#
#33124
1#
#33176
0#
#33228
1#
#33280
0#
#33332
1#
#33384
0#
#33436
1#
#33488
0#
#33540
1#
#33592
0#
#33644
1#
#33696
0#
#33748
1#
#33800
0#
#33852
1#
#33904
0#
#33956
1#
#34008
0#
#34060
1#
#34112
0#
#34164
1#
#34216
0#
#34268
1#
#34320
0#
#34372
1#
#34424
0#
#34476
1#
#34528
0#
#34580
1#
#34632
0#
#34684
1#
#34736
0#
#34788
1#
#34840
0#
#34892
1#
#34944
0#
#34996
1#
#35048
0#
#35100
1#
#35152
0#
#35204
1#
#35256
0#
#35308
1#
#35360
0#
#35412
1#
#35464
0#
#35516
1#
#35568
0#
#35620
1#
#35672
0#
#35724
1#
#35776
0#
#35828
1#
#35880
0#
#35932
1#
#35984
0#
#36036
1#
#36088
0#
#36140
1#
#36192
0#
#36244
1#
#36296
0#
#36348
1#
#36400
0#
#36452
1#
#36504
0#
#36556
1#
#36608
0#
#36660
1#
#36712
0#
#36764
1#
#36816
0#
#36868
1#
#36920
0#
#36972
1#
#37024
0#
#37076
1#
#37128
0#
#37180
1#
#37232
0#
#37284
1#
#37336
0#
#37388
1#
#37440
0#
#37492
1#
#37544
0#
#37596
1#
#37648
0#
#37700
1#
#37752
0#
#37804
1#
#37856
0#
#37908
1#
#37960
0#
#38012
1#
#38064
0#
#38116
1#
#38168
0#
#38220
1#
#38272
0#
#38324
1#
#38376
0#
#38428
1#
#38480
0#
#38532
1#
#38584
0#
#38636
1#
#38688
0#
#38740
1#
#38792
0#
#38844
1#
#38896
0#
#38948
1#
#39000
0#
#39052
1#
#39104
0#
#39156
1#
#39208
0#
#39260
1#
#39312
0#
#39364
1#
#39416
0#
#39468
1#
#39520
0#
#39572
1#
#39624
0#
#39676
1#
#39728
0#
#39780
1#
#39832
0#
#39884
1#
#39936
0#
#39988
1#
#40040
0#
#40092
1#
#40144
0#
#40196
1#
#40248
0#
#40300
1#
#40352
0#
#40404
1#
#40456
0#
#40508
1#
#40560
0#
#40612
1#
#40664
0#
#40716
1#
#40768
0#
#40820
1#
#40872
0#
#40924
1#
#40976
0#
#41028
1#
#41080
0#
#41132
1#
#41184
0#
#41236
1#
#41288
0#
#41340
1#
#41392
0#
#41444
1#
#41496
0#
#41548
1#
#41600
0#
#41652
1#
#41704
0#
#41756
1#
#41808
0#
#41860
1#
#41912
0#
#41964
1#
#42016
0#
#42068
1#
#42120
0#
#42172
1#
#42224
0#
#42276
1#
#42328
0#
#42380
1#
#42432
0#
#42484
1#
#42536
0#
#42588
1#
#42640
0#
#42692
1#
#42744
0#
#42796
1#
#42848
0#
#42900
1#
#42952
0#
#43004
1#
#43056
0#
#43108
1#
#43160
0#
#43212
1#
#43264
0#
#43316
1#
#43368
0#
#43420
1#
#43472
0#
#43524
1#
#43576
0#
#43628
1#
#43680
0#
#43732
1#
#43784
0#
#43836
1#
#43888
0#
#43940
1#
#43992
0#
#44044
1#
#44096
0#
#44148
1#
#44200
0#
#44252
1#
#44304
0#
#44356
1#
#44408
0#
#44460
1#
#44512
0#
#44564
1#
#44616
0#
#44668
1#
#44720
0#
#44772
1#
#44824
0#
#44876
1#
#44928
0#
#44980
1#
#45032
0#
#45084
1#
#45136
0#
#45188
1#
#45240
0#
#45292
1#
#45344
0#
#45396
1#
#45448
0#
#45500
1#
#45552
0#
#45604
1#
#45656
0#
#45708
1#
#45760
0#
#45812
1#
#45864
0#
#45916
1#
#45968
0#
#46020
1#
#46072
0#
#46124
1#
#46176
0#
#46228
1#
#46280
0#
#46332
1#
#46384
0#
#46436
1#
#46488
0#
#46540
1#
#46592
0#
#46644
1#
#46696
0#
#46748
1#
#46800
0#
#46852
1#
#46904
0#
#46956
1#
#47008
0#
#47060
1#
#47112
0#
#47164
1#
#47216
0#
#47268
1#
#47320
0#
#47372
1#
#47424
0#
#47476
1#
#47528
0#
#47580
1#
#47632
0#
#47684
1#
#47736
0#
#47788
1#
#47840
0#
#47892
1#
#47944
0#
#47996
1#
#48048
0#
#48100
1#
#48152
0#
#48204
1#
#48256
0#
#48308
1#
#48360
0#
#48412
1#
#48464
0#
#48516
1#
#48568
0#
#48620
1#
#48672
0#
#48724
1#
#48776
0#
#48828
1#
#48880
0#
#48932
1#
#48984
0#
#49036
1#
#49088
0#
#49140
1#
#49192
0#
#49244
1#
#49296
0#
#49348
1#
#49400
0#
#49452
1#
#49504
0#
#49556
1#
#49608
0#
#49660
1#
#49712
0#
#49764
1#
#49816
0#
#49868
1#
#49920
0#
#49972
1#
#50024
0#
#50076
1#
#50128
0#
#50180
1#
#50232
0#
#50284
1#
#50336
0#
#50388
1#
#50440
0#
#50492
1#
#50544
0#
#50596
1#
#50648
0#
#50700
1#
#50752
0#
#50804
1#
#50856
0#
#50908
1#
#50960
0#
#51012
1#
#51064
0#
#51116
1#
#51168
0#
#51220
1#
#51272
0#
#51324
1#
#51376
0#
#51428
1#
#51480
0#
#51532
1#
#51584
0#
#51636
1#
#51688
0#
#51740
1#
#51792
0#
#51844
1#
#51896
0#
#51948
1#
#52000
0#
#52052
1#
#52104
0#
#52156
1#
#52208
0#
#52260
1#
#52312
0#
#52364
1#
#52416
0#
#52468
1#
#52520
0#
#52572
1#
#52624
0#
#52676
1#
#52728
0#
#52780
1#
#52832
0#
#52884
1#
#52936
0#
#52988
1#
#53040
0#
#53092
1#
#53144
0#
#53196
1#
#53248
0#
#53300
1#
#53352
0#
#53404
1#
#53456
0#
#53508
1#
#53560
0#
#53612
1#
#53664
0#
#53716
1#
#53768
0#
#53820
1#
#53872
0#
#53924
1#
#53976
0#
#54028
1#
#54080
0#
#54132
1#
#54184
0#
#54236
1#
#54288
0#
#54340
1#
#54392
0#
#54444
1#
#54496
0#
#54548
1#
#54600
0#
#54652
1#
#54704
0#
#54756
1#
#54808
0#
#54860
1#
#54912
0#
#54964
1#
#55016
0#
#55068
1#
#55120
0#
#55172
1#
#55224
0#
#55276
1#
#55328
0#
#55380
1#
#55432
0#
#55484
1#
#55536
0#
#55588
1#
#55640
0#
#55692
1#
#55744
0#
#55796
1#
#55848
0#
#55900
1#
#55952
0#
#56004
1#
#56056
0#
#56108
1#
#56160
0#
#56212
1#
#56264
0#
#56316
1#
#56368
0#
#56420
1#
#56472
0#
#56524
1#
#56576
0#
#56628
1#
#56680
0#
#56732
1#
#56784
0#
#56836
1#
#56888
0#
#56940
1#
#56992
0#
#57044
1#
#57096
0#
#57148
1#
#57200
0#
#57252
1#
#57304
0#
#57356
1#
#57408
0#
#57460
1#
#57512
0#
#57564
1#
#57616
0#
#57668
1#
#57720
0#
#57772
1#
#57824
0#
#57876
1#
#57928
0#
#57980
1#
#58032
0#
#58084
1#
#58136
0#
#58188
1#
#58240
0#
#58292
1#
#58344
0#
#58396
1#
#58448
0#
#58500
1#
#58552
0#
#58604
1#
#58656
0#
#58708
1#
#58760
0#
#58812
1#
#58864
0#
#58916
1#
#58968
0#
#59020
1#
#59072
0#
#59124
1#
#59176
0#
#59228
1#
#59280
0#
#59332
1#
#59384
0#
#59436
1#
#59488
0#
#59540
1#
#59592
0#
#59644
1#
#59696
0#
#59748
1#
#59800
0#
#59852
1#
#59904
0#
#59956
1#
#60008
0#
#60060
1#
#60112
0#
#60164
1#
#60216
0#
#60268
1#
#60320
0#
#60372
1#
#60424
0#
#60476
1#
#60528
0#
#60580
1#
#60632
0#
#60684
1#
#60736
0#
#60788
1#
#60840
0#
#60892
1#
#60944
0#
#60996
1#
#61048
0#
#61100
1#
#61152
0#
#61204
1#
#61256
0#
#61308
1#
#61360
0#
#61412
1#
#61464
0#
#61516
1#
#61568
0#
#61620
1#
#61672
0#
#61724
1#
#61776
0#
#61828
1#
#61880
0#
#61932
1#
#61984
0#
#62036
1#
#62088
0#
#62140
1#
#62192
0#
#62244
1#
#62296
0#
#62348
1#
#62400
0#
#62452
1#
#62504
0#
#62556
1#
#62608
0#
#62660
1#
#62712
0#
#62764
1#
#62816
0#
#62868
1#
#62920
0#
#62972
1#
#63024
0#
#63076
1#
#63128
0#
#63180
1#
#63232
0#
#63284
1#
#63336
0#
#63388
1#
#63440
0#
#63492
1#
#63544
0#
#63596
1#
#63648
0#
#63700
1#
#63752
0#
#63804
1#
#63856
0#
#63908
1#
#63960
0#
#64012
1#
#64064
0#
#64116
1#
#64168
0#
#64220
1#
#64272
0#
#64324
1#
#64376
0#
#64428
1#
#64480
0#
#64532
1#
#64584
0#
#64636
1#
#64688
0#
#64740
1#
#64792
0#
#64844
1#
#64896
0#
#64948
1#
#65000
0#
#65052
1#
#65104
0#
#65156
1#
#65208
0#
#65260
1#
#65312
0#
#65364
1#
#65416
0#
#65468
1#
#65520
0#
#65572
1#
#65624
0#
#65676
1#
#65728
0#
#65780
1#
#65832
0#
#65884
1#
#65936
0#
#65988
1#
#66040
0#
#66092
1#
#66144
0#
#66196
1#
#66248
0#
#66300
1#
#66352
0#
#66404
1#
#66456
0#
#66508
1#
#66560
0#
#66612
1#
#66664
0#
#66716
1#
#66768
0#
#66820
1#
#66872
0#
#66924
1#
#66976
0#
#67028
1#
#67080
0#
#67132
1#
#67184
0#
#67236
1#
#67288
0#
#67340
1#
#67392
0#
#67444
1#
#67496
0#
#67548
1#
#67600
0#
#67652
1#
#67704
0#
#67756
1#
#67808
0#
#67860
1#
#67912
0#
#67964
1#
#68016
0#
#68068
1#
#68120
0#
#68172
1#
#68224
0#
#68276
1#
#68328
0#
#68380
1#
#68432
0#
#68484
1#
#68536
0#
#68588
1#
#68640
0#
#68692
1#
#68744
0#
#68796
1#
#68848
0#
#68900
1#
#68952
0#
#69004
1#
#69056
0#
#69108
1#
#69160
0#
#69212
1#
#69264
0#
#69316
1#
#69368
0#
#69420
1#
#69472
0#
#69524
1#
#69576
0#
#69628
1#
#69680
0#
#69732
1#
#69784
0#
#69836
1#
#69888
0#
#69940
1#
#69992
0#
#70044
1#
#70096
0#
#70148
1#
#70200
0#
#70252
1#
#70304
0#
#70356
1#
#70408
0#
#70460
1#
#70512
0#
#70564
1#
#70616
0#
#70668
1#
#70720
0#
#70772
1#
#70824
0#
#70876
1#
#70928
0#
#70980
1#
#71032
0#
#71084
1#
#71136
0#
#71188
1#
#71240
0#
#71292
1#
#71344
0#
#71396
1#
#71448
0#
#71500
1#
#71552
0#
#71604
1#
#71656
0#
#71708
1#
#71760
0#
#71812
1#
#71864
0#
#71916
1#
#71968
0#
#72020
1#
#72072
0#
#72124
1#
#72176
0#
#72228
1#
#72280
0#
#72332
1#
#72384
0#
#72436
1#
#72488
0#
#72540
1#
#72592
0#
#72644
1#
#72696
0#
#72748
1#
#72800
0#
#72852
1#
#72904
0#
#72956
1#
#73008
0#
#73060
1#
#73112
0#
#73164
1#
#73216
0#
#73268
1#
#73320
0#
#73372
1#
#73424
0#
#73476
1#
#73528
0#
#73580
1#
#73632
0#
#73684
1#
#73736
0#
#73788
1#
#73840
0#
#73892
1#
#73944
0#
#73996
1#
#74048
0#
#74100
1#
#74152
0#
#74204
1#
#74256
0#
#74308
1#
#74360
0#
#74412
1#
#74464
0#
#74516
1#
#74568
0#
#74620
1#
#74672
0#
#74724
1#
#74776
0#
#74828
1#
#74880
0#
#74932
1#
#74984
0#
#75036
1#
#75088
0#
#75140
1#
#75192
0#
#75244
1#
#75296
0#
#75348
1#
#75400
0#
#75452
1#
#75504
0#
#75556
1#
#75608
0#
#75660
1#
#75712
0#
#75764
1#
#75816
0#
#75868
1#
#75920
0#
#75972
1#
#76024
0#
#76076
1#
#76128
0#
#76180
1#
#76232
0#
#76284
1#
#76336
0#
#76388
1#
#76440
0#
#76492
1#
#76544
0#
#76596
1#
#76648
0#
#76700
1#
#76752
0#
#76804
1#
#76856
0#
#76908
1#
#76960
0#
#77012
1#
#77064
0#
#77116
1#
#77168
0#
#77220
1#
#77272
0#
#77324
1#
#77376
0#
#77428
1#
#77480
0#
#77532
1#
#77584
0#
#77636
1#
#77688
0#
#77740
1#
#77792
0#
#77844
1#
#77896
0#
#77948
1#
#78000
0#
#78052
1#
#78104
0#
#78156
1#
#78208
0#
#78260
1#
#78312
0#
#78364
1#
#78416
0#
#78468
1#
#78520
0#
#78572
1#
#78624
0#
#78676
1#
#78728
0#
#78780
1#
#78832
0#
#78884
1#
#78936
0#
#78988
1#
#79040
0#
#79092
1#
#79144
0#
#79196
1#
#79248
0#
#79300
1#
#79352
0#
#79404
1#
#79456
0#
#79508
1#
#79560
0#
#79612
1#
#79664
0#
#79716
1#
#79768
0#
#79820
1#
#79872
0#
#79924
1#
#79976
0#
#80028
1#
#80080
0#
#80132
1#
#80184
0#
#80236
1#
#80288
0#
#80340
1#
#80392
0#
#80444
1#
#80496
0#
#80548
1#
#80600
0#
#80652
1#
#80704
0#
#80756
1#
#80808
0#
#80860
1#
#80912
0#
#80964
1#
#81016
0#
#81068
1#
#81120
0#
#81172
1#
#81224
0#
#81276
1#
#81328
0#
#81380
1#
#81432
0#
#81484
1#
#81536
0#
#81588
1#
#81640
0#
#81692
1#
#81744
0#
#81796
1#
#81848
0#
#81900
1#
#81952
0#
#82004
1#
#82056
0#
#82108
1#
#82160
0#
#82212
1#
#82264
0#
#82316
1#
#82368
0#
#82420
1#
#82472
0#
#82524
1#
#82576
0#
#82628
1#
#82680
0#
#82732
1#
#82784
0#
#82836
1#
#82888
0#
#82940
1#
#82992
0#
#83044
1#
#83096
0#
#83148
1#
#83200
0#
#83252
1#
#83304
0#
#83356
1#
#83408
0#
#83460
1#
#83512
0#
#83564
1#
#83616
0#
#83668
1#
#83720
0#
#83772
1#
#83824
0#
#83876
1#
#83928
0#
#83980
1#
#84032
0#
#84084
1#
#84136
0#
#84188
1#
#84240
0#
#84292
1#
#84344
0#
#84396
1#
#84448
0#
#84500
1#
#84552
0#
#84604
1#
#84656
0#
#84708
1#
#84760
0#
#84812
1#
#84864
0#
#84916
1#
#84968
0#
#85020
1#
#85072
0#
#85124
1#
#85176
0#
#85228
1#
#85280
0#
#85332
1#
#85384
0#
#85436
1#
#85488
0#
#85540
1#
#85592
0#
#85644
1#
#85696
0#
#85748
1#
#85800
0#
#85852
1#
#85904
0#
#85956
1#
#86008
0#
#86060
1#
#86112
0#
#86164
1#
#86216
0#
#86268
1#
#86320
0#
#86372
1#
#86424
0#
#86476
1#
#86528
0#
#86580
1#
#86632
0#
#86684
1#
#86736
0#
#86788
1#
#86840
0#
#86892
1#
#86944
0#
#86996
1#
#87048
0#
#87100
1#
#87152
0#
#87204
1#
#87256
0#
#87308
1#
#87360
0#
#87412
1#
#87464
0#
#87516
1#
#87568
0#
#87620
1#
#87672
0#
#87724
1#
#87776
0#
#87828
1#
#87880
0#
#87932
1#
#87984
0#
#88036
1#
#88088
0#
#88140
1#
#88192
0#
#88244
1#
#88296
0#
#88348
1#
#88400
0#
#88452
1#
#88504
0#
#88556
1#
#88608
0#
#88660
1#
#88712
0#
#88764
1#
#88816
0#
#88868
1#
#88920
0#
#88972
1#
#89024
0#
#89076
1#
#89128
0#
#89180
1#
#89232
0#
#89284
1#
#89336
0#
#89388
1#
#89440
0#
#89492
1#
#89544
0#
#89596
1#
#89648
0#
#89700
1#
#89752
0#
#89804
1#
#89856
0#
#89908
1#
#89960
0#
#90012
1#
#90064
0#
#90116
1#
#90168
0#
#90220
1#
#90272
0#
#90324
1#
#90376
0#
#90428
1#
#90480
0#
#90532
1#
#90584
0#
#90636
1#
#90688
0#
#90740
1#
#90792
0#
#90844
1#
#90896
0#
#90948
1#
#91000
0#
#91052
1#
#91104
0#
#91156
1#
#91208
0#
#91260
1#
#91312
0#
#91364
1#
#91416
0#
#91468
1#
#91520
0#
#91572
1#
#91624
0#
#91676
1#
#91728
0#
#91780
1#
#91832
0#
#91884
1#
#91936
0#
#91988
1#
#92040
0#
#92092
1#
#92144
0#
#92196
1#
#92248
0#
#92300
1#
#92352
0#
#92404
1#
#92456
0#
#92508
1#
#92560
0#
#92612
1#
#92664
0#
#92716
1#
#92768
0#
#92820
1#
#92872
0#
#92924
1#
#92976
0#
#93028
1#
#93080
0#
#93132
1#
#93184
0#
#93236
1#
#93288
0#
#93340
1#
#93392
0#
#93444
1#
#93496
0#
#93548
1#
#93600
0#
#93652
1#
#93704
0#
#93756
1#
#93808
0#
#93860
1#
#93912
0#
#93964
1#
#94016
0#
#94068
1#
#94120
0#
#94172
1#
#94224
0#
#94276
1#
#94328
0#
#94380
1#
#94432
0#
#94484
1#
#94536
0#
#94588
1#
#94640
0#
#94692
1#
#94744
0#
#94796
1#
#94848
0#
#94900
1#
#94952
0#
#95004
1#
#95056
0#
#95108
1#
#95160
0#
#95212
1#
#95264
0#
#95316
1#
#95368
0#
#95420
1#
#95472
0#
#95524
1#
#95576
0#
#95628
1#
#95680
0#
#95732
1#
#95784
0#
#95836
1#
#95888
0#
#95940
1#
#95992
0#
#96044
1#
#96096
0#
#96148
1#
#96200
0#
#96252
1#
#96304
0#
#96356
1#
#96408
0#
#96460
1#
#96512
0#
#96564
1#
#96616
0#
#96668
1#
#96720
0#
#96772
1#
#96824
0#
#96876
1#
#96928
0#
#96980
1#
#97032
0#
#97084
1#
#97136
0#
#97188
1#
#97240
0#
#97292
1#
#97344
0#
#97396
1#
#97448
0#
#97500
1#
#97552
0#
#97604
1#
#97656
0#
#97708
1#
#97760
0#
#97812
1#
#97864
0#
#97916
1#
#97968
0#
#98020
1#
#98072
0#
#98124
1#
#98176
0#
#98228
1#
#98280
0#
#98332
1#
#98384
0#
#98436
1#
#98488
0#
#98540
1#
#98592
0#
#98644
1#
#98696
0#
#98748
1#
#98800
0#
#98852
1#
#98904
0#
#98956
1#
#99008
0#
